<?xml version="1.0" encoding="UTF-8"?>
<ExtensionModel>

	<Extension path = "/MonoDevelop/Ide/Commands/VersionControl">
		<Command id = "ShowInGithub.Commands.ShowInGithub"
		         defaultHandler = "ShowInGithub.ShowInGithubCommand"
		         _label = "Show in Github" /> 
		<Command id = "ShowInGithub.Commands.CopyGithubLink"
		         defaultHandler = "ShowInGithub.CopyGithubLinkCommand"
		         _label = "Copy Github Link" /> 
	</Extension>

	<Extension path = "/MonoDevelop/SourceEditor2/ContextMenu/Editor">
		<SeparatorItem />
		<CommandItem id = "ShowInGithub.Commands.ShowInGithub" />
		<CommandItem id = "ShowInGithub.Commands.CopyGithubLink" />
		<SeparatorItem />
	</Extension>

</ExtensionModel>
